prismh.core-0.4.0-py2.7-nspkg.pth
prismh/core/__init__.py
prismh/core/scripts.py
prismh/core/output/__init__.py
prismh/core/output/assessment.py
prismh/core/output/calculationset.py
prismh/core/output/common.py
prismh/core/output/form.py
prismh/core/output/instrument.py
prismh/core/output/interaction.py
prismh/core/validation/__init__.py
prismh/core/validation/assessment.py
prismh/core/validation/calculationset.py
prismh/core/validation/common.py
prismh/core/validation/form.py
prismh/core/validation/instrument.py
prismh/core/validation/interaction.py
prismh.core-0.4.0.dist-info/DESCRIPTION.rst
prismh.core-0.4.0.dist-info/entry_points.txt
prismh.core-0.4.0.dist-info/METADATA
prismh.core-0.4.0.dist-info/metadata.json
prismh.core-0.4.0.dist-info/namespace_packages.txt
prismh.core-0.4.0.dist-info/RECORD
prismh.core-0.4.0.dist-info/top_level.txt
prismh.core-0.4.0.dist-info/WHEEL
prismh.core-0.4.0.dist-info/zip-safe
