Metadata-Version: 2.0
Name: prismh.core
Version: 0.4.0
Summary: Parsing and Validation library for PRISMH Files
Home-page: https://bitbucket.org/prometheus/prismh.core
Author: Prometheus Research, LLC
Author-email: contact@prometheusresearch.com
License: AGPLv3
Keywords: prismh instrument assessment validation
Platform: UNKNOWN
Classifier: Intended Audience :: Developers
Classifier: License :: OSI Approved :: GNU Affero General Public License v3
Classifier: Programming Language :: Python :: 2.6
Classifier: Programming Language :: Python :: 2.7
Classifier: Programming Language :: Python :: 3.2
Classifier: Programming Language :: Python :: 3.3
Classifier: Programming Language :: Python :: 3.4
Requires-Dist: six (>=1.5,<2)
Requires-Dist: colander (>=1.0,<1.1)
Requires-Dist: pyyaml
Provides-Extra: dev
Requires-Dist: coverage (>=3.7,<4); extra == 'dev'
Requires-Dist: nose (>=1.3,<2); extra == 'dev'
Requires-Dist: nosy (>=1.1,<2); extra == 'dev'
Requires-Dist: prospector[with_pyroma] (>=0.10,<0.11); extra == 'dev'
Requires-Dist: twine (>=1.5,<2); extra == 'dev'
Requires-Dist: wheel (>=0.24,<0.25); extra == 'dev'
Requires-Dist: Sphinx (>=1.3,<2); extra == 'dev'
Requires-Dist: sphinx-autobuild (>=0.5,<0.6); extra == 'dev'
Requires-Dist: tox (>=2,<3); extra == 'dev'
Requires-Dist: HTSQL (>=2.3,<2.4); extra == 'dev'
